LICENSE.md
MANIFEST.in
README.md
requirements.txt
setup.cfg
setup.py
doc/Makefile
doc/make.bat
doc/source/FAQ.rst
doc/source/accuracy.rst
doc/source/algobase.rst
doc/source/basic_algorithms.rst
doc/source/building_custom_algo.rst
doc/source/co_clustering.rst
doc/source/conf.py
doc/source/dataset.rst
doc/source/dump.rst
doc/source/getting_started.rst
doc/source/index.rst
doc/source/knn_inspired.rst
doc/source/matrix_factorization.rst
doc/source/model_selection.rst
doc/source/notation_standards.rst
doc/source/prediction_algorithms.rst
doc/source/prediction_algorithms_package.rst
doc/source/predictions_module.rst
doc/source/reader.rst
doc/source/refs.bib
doc/source/similarities.rst
doc/source/slope_one.rst
doc/source/spelling_wordlist.txt
doc/source/trainset.rst
examples/baselines_conf.py
examples/basic_usage.py
examples/benchmark.py
examples/evaluate_on_trainset.py
examples/generate_grid_search_cv_results_example.py
examples/grid_search_usage.py
examples/k_nearest_neighbors.py
examples/load_custom_dataset.py
examples/load_custom_dataset_predefined_folds.py
examples/load_from_dataframe.py
examples/precision_recall_at_k.py
examples/predict_ratings.py
examples/run_all_examples.py
examples/serialize_algorithm.py
examples/similarity_conf.py
examples/split_data_for_unbiased_estimation.py
examples/top_n_recommendations.py
examples/train_test_split.py
examples/use_cross_validation_iterators.py
examples/building_custom_algorithms/mean_rating_user_item.py
examples/building_custom_algorithms/most_basic_algorithm.py
examples/building_custom_algorithms/most_basic_algorithm2.py
examples/building_custom_algorithms/with_baselines_or_sim.py
examples/notebooks/Compare.ipynb
examples/notebooks/KNNBasic_analysis.ipynb
scikit_my_surprise.egg-info/PKG-INFO
scikit_my_surprise.egg-info/SOURCES.txt
scikit_my_surprise.egg-info/dependency_links.txt
scikit_my_surprise.egg-info/entry_points.txt
scikit_my_surprise.egg-info/requires.txt
scikit_my_surprise.egg-info/top_level.txt
surprise/__init__.py
surprise/__main__.py
surprise/accuracy.py
surprise/builtin_datasets.py
surprise/dataset.py
surprise/dump.py
surprise/reader.py
surprise/similarities.c
surprise/similarities.pyx
surprise/trainset.py
surprise/utils.py
surprise/model_selection/__init__.py
