Metadata-Version: 2.1
Name: scikit-my-surprise
Version: 1.1.1
Summary: An easy-to-use library for recommender systems.
Home-page: http://surpriselib.com
Author: Nicolas Hug, William La Cava
Author-email: contact@nicolas-hug.com
License: GPLv3+
Keywords: recommender recommendation system
Platform: UNKNOWN
Classifier: Development Status :: 5 - Production/Stable
Classifier: Intended Audience :: Developers
Classifier: Intended Audience :: Education
Classifier: Intended Audience :: Science/Research
Classifier: Topic :: Scientific/Engineering
Classifier: License :: OSI Approved :: BSD License
Classifier: Programming Language :: Python :: 3
Classifier: Programming Language :: Python :: 2.7
